easy_m3u8/__init__.py
easy_m3u8/demo.py
easy_m3u8-1.0.dist-info/METADATA
easy_m3u8-1.0.dist-info/WHEEL
easy_m3u8-1.0.dist-info/top_level.txt
easy_m3u8-1.0.dist-info/RECORD
