Metadata-Version: 2.1
Name: easy-m3u8
Version: 1.0
Requires-Dist: requests
Requires-Dist: pycryptodome
